{
  "version": 1,
  "audio": "14_Section_9.mp3",
  "section_id": "section-9",
  "sentence_count": 10,
  "duration": 215.611,
  "sentences": [
    {
      "start": 19.723,
      "end": 29.302,
      "text": "The Shepherd\u2019s voice still pierces systems and centuries; his sheep recognize the sound."
    },
    {
      "start": 30.063,
      "end": 40.277,
      "text": "The Holy Spirit now stands unveiled as the only begotten God\u2014the cornerstone rejected by the builders, now revealed as the foundation of his true assembly."
    },
    {
      "start": 41.578,
      "end": 51.063,
      "text": "This is not theory or reformulation but the testimony of the Spirit, disclosed to those who have received the Son."
    },
    {
      "start": 51.964,
      "end": 68.212,
      "text": "By divine appointment, this foundation reemerges\u2014not as new doctrine, but as the original apostolic faith restored in an age unlike any before it: a time when one voice can speak to the nations in every tongue."
    },
    {
      "start": 68.952,
      "end": 83.399,
      "text": "The gospel that must reach all the world before Christ\u2019s return will be carried not by the strength of men but by the power of his Spirit, who now calls to his own: \u201cCome out from her, my people.\u201d"
    },
    {
      "start": 84.3,
      "end": 87.722,
      "text": "The scroll sealed until the time of the end is now open."
    },
    {
      "start": 88.782,
      "end": 103.11,
      "text": "For centuries, powerful forces sought to obscure the Way\u2014through the slaughter of his followers, the destruction of Spirit-inspired writings, and sorceries passed down from the fallen Watchers."
    },
    {
      "start": 104.05,
      "end": 118.021,
      "text": "Yet the Father has unveiled to this generation what was long preserved in the sacred writings: the revelation of his Son, now breaking forth to unite his people, Jew and Gentile alike."
    },
    {
      "start": 118.942,
      "end": 125.327,
      "text": "And this is the testimony of Christ himself: \u201cI am the way, the truth, and the life."
    },
    {
      "start": 126.127,
      "end": 130.19,
      "text": "No one comes to the Father except through me\u201d (John 14:6)."
    }
  ]
}